tcga/__init__.py
tcga/codons/__init__.py
tcga/codons/codons.py
tcga/codons/static/parsed/tables.pkl.zip
tcga/complements/__init__.py
tcga/complements/complements.py
tcga/data/__init__.py
tcga/data/aaindex/__init__.py
tcga/data/aaindex/aaindex.py
tcga/data/aaindex/static/parsed/aaindex.pkl.zip
tcga/data/blosum/__init__.py
tcga/data/blosum/blosum.py
tcga/data/genesets/__init__.py
tcga/data/sa_aa_ref_chart/__init__.py
tcga/data/sa_aa_ref_chart/tables.py
tcga/fake/__init__.py
tcga/fake/gamma_nb.py
tcga/refs/__init__.py
tcga/refs/annotations.py
tcga/strings/__init__.py
tcga/strings/pearls.py
tcga/utils/__init__.py
tcga/utils/circular.py
tcga/utils/containers.py
tcga/utils/download.py
tcga/utils/files.py
tcga/utils/first.py
tcga/utils/meta.py
tcga/utils/peek.py
tcga-0.0.22.dist-info/LICENSE
tcga-0.0.22.dist-info/METADATA
tcga-0.0.22.dist-info/WHEEL
tcga-0.0.22.dist-info/top_level.txt
tcga-0.0.22.dist-info/RECORD
