Metadata-Version: 2.1
Name: tcga
Version: 0.0.22
Summary: Computational biology & bioinformatics utils
Home-page: https://github.com/numpde/tcga
Author: RA
Author-email: numpde@null.net
License: UNKNOWN
Keywords: computational biology bioinformatics genetics
Platform: UNKNOWN
Classifier: Programming Language :: Python :: 3
Classifier: License :: OSI Approved :: MIT License
Classifier: Operating System :: OS Independent
Requires-Python: >=3.6
